a2as/__init__.py
a2as/core.py
a2as-0.1.0.dist-info/licenses/LICENSE
a2as-0.1.0.dist-info/METADATA
a2as-0.1.0.dist-info/WHEEL
a2as-0.1.0.dist-info/top_level.txt
a2as-0.1.0.dist-info/RECORD
